{"archive":"1","matchID":"7ee92c7e-4fdd-42a9-a5db-9a89d7957383","matchIDinofficial":"20180516WED7","matchNum":"7","matchDate":"2018-05-16+08:00","matchDay":"WED","coupon":{"couponID":"5","couponShortName":"WED","couponNameCH":"周三賽事","couponNameEN":"Wednesday Matches"},"league":{"leagueID":"65","leagueShortName":"JLC","leagueNameCH":"日本聯賽盃","leagueNameEN":"Japanese League Cup"},"homeTeam":{"teamID":"796","teamNameCH":"甲府風林","teamNameEN":"Ventforet Kofu"},"awayTeam":{"teamID":"545","teamNameCH":"磐田山葉","teamNameEN":"Jubilo Iwata"},"matchStatus":"ResultIn","matchTime":"2018-05-16T18:00:00+08:00","statuslastupdated":"2018-05-16T20:25:13+08:00","inplaydelay":"false","liveEvent":{"ilcLiveDisplay":true,"hasLiveInfo":true,"isIncomplete":false,"matchIDbetradar":"13874439","matchstate":"EndedAfterFT","stateTS":"2018-05-16T19:04:14+08:00","liveevent":[{"order":1,"minutesElasped":"7","actionType":"Regular","playerNameCH":"櫻內渚","playerNameEN":"Nagisa Sakurauchi","homeaway":"Away"},{"order":2,"minutesElasped":"61","actionType":"YellowCard","playerNameCH":"","playerNameEN":"Kota Mori","homeaway":"Home"},{"order":3,"minutesElasped":"85","actionType":"YellowCard","playerNameCH":"","playerNameEN":"Hiroki Ito","homeaway":"Away"},{"order":4,"minutesElasped":"87","actionType":"YellowCard","playerNameCH":"","playerNameEN":"Takuma Ominami","homeaway":"Away"},{"order":5,"minutesElasped":"90","actionType":"YellowCard","playerNameCH":"","playerNameEN":"Ryuki Miura","homeaway":"Away"}]},"accumulatedscore":[{"periodvalue":"FirstHalf","periodstatus":"ResultFinal","home":"0","away":"1"},{"periodvalue":"SecondHalf","periodstatus":"ResultFinal","home":"0","away":"1"}],"livescore":{"home":"0","away":"1"},"cornerresult":"","Cur":"1","hasWebTV":false,"hadodds":{"D":"100@3.25","A":"100@2.20","H":"100@2.77","ID":"a6dee1a8-975a-44a5-bf4b-6929528190f1","POOLSTATUS":"Payout","INPLAY":"false","ALLUP":"true","Cur":"1"},"fhaodds":{"H":"100@3.60","D":"100@1.95","A":"100@2.95","ID":"11502fe3-faed-49fc-9b92-cf3364351914","POOLSTATUS":"Payout","INPLAY":"false","ALLUP":"true","Cur":"1"},"crsodds":{"S0005":"100@150.0","SM1MH":"100@100.0","S0401":"100@60.00","SM1MA":"100@80.00","S0000":"100@9.50","S0500":"100@250.0","S0100":"100@8.00","S0502":"100@300.0","S0003":"100@20.00","S0203":"100@26.00","S0001":"100@7.00","SM1MD":"100@400.0","S0200":"100@13.00","S0202":"100@14.00","S0402":"100@80.00","S0400":"100@80.00","S0102":"100@7.50","S0104":"100@40.00","S0501":"100@250.0","S0105":"100@120.0","S0300":"100@30.00","S0101":"100@6.25","S0302":"100@30.00","S0004":"100@50.00","S0103":"100@17.00","S0201":"100@8.75","S0002":"100@10.00","S0204":"100@70.00","S0205":"100@250.0","S0303":"100@60.00","S0301":"100@23.00","ID":"62744903-1a71-4f95-94f3-1e98a4c9301c","POOLSTATUS":"Payout","INPLAY":"false","ALLUP":"true","Cur":"1"},"fcsodds":{"S0501":"100@2000","S0004":"100@250.0","S0302":"100@300.0","S0202":"100@70.00","S0204":"100@900.0","S0402":"100@900.0","S0002":"100@12.00","S0105":"100@1000","S0301":"100@120.0","S0200":"100@17.00","S0303":"100@800.0","S0101":"100@7.50","S0005":"100@900.0","S0400":"100@400.0","S0003":"100@50.00","SM1MH":"100@2000","S0203":"100@250.0","S0100":"100@4.50","S0103":"100@80.00","S0205":"100@4000","S0500":"100@1000","S0104":"100@400.0","S0401":"100@600.0","S0201":"100@25.00","S0000":"100@2.40","SM1MA":"100@1000","SM1MD":"100@5000","S0502":"100@5000","S0001":"100@3.85","S0102":"100@21.00","S0300":"100@70.00","ID":"f4f7591d-9aa9-42e0-ae06-5c1db3403e26","POOLSTATUS":"Payout","INPLAY":"false","ALLUP":"true","Cur":"1"},"ftsodds":{"H":"100@2.11","A":"100@1.82","N":"100@9.50","ID":"15964453-c866-49fa-a8e6-544a0c873aa5","POOLSTATUS":"Payout","INPLAY":"false","ALLUP":"true","Cur":"1"},"ooeodds":{"E":"100@1.80","O":"100@1.90","ID":"ae4ebadf-f14a-4d85-8b3a-3cb0bf6f5731","POOLSTATUS":"Payout","INPLAY":"false","ALLUP":"true","Cur":"1"},"ttgodds":{"P3":"100@3.75","M7":"100@30.00","P0":"100@9.50","P2":"100@3.35","P5":"100@11.00","P6":"100@20.00","P1":"100@4.00","P4":"100@6.10","ID":"1c181916-db9d-4037-92a5-203d2ae6f971","POOLSTATUS":"Payout","INPLAY":"false","ALLUP":"true","Cur":"1"},"hftodds":{"AH":"100@34.00","HD":"100@13.00","AD":"100@13.00","DH":"100@6.50","DD":"100@4.80","HA":"100@29.00","AA":"100@3.60","HH":"100@4.80","DA":"100@5.20","ID":"65392d8c-4581-463f-955f-efd6a401a9e2","POOLSTATUS":"Payout","INPLAY":"false","ALLUP":"true","Cur":"1"},"hhaodds":{"D":"100@3.70","A":"100@4.50","H":"100@1.57","ID":"18ca747b-eae4-404a-9537-1ba197948098","POOLSTATUS":"Payout","INPLAY":"false","ALLUP":"true","HG":"+1","AG":"-1","Cur":"1"},"hilodds":{"LINELIST":[{"LINENUM":"1","MAINLINE":"true","LINESTATUS":"1","LINEORDER":"1","LINE":"2.5/2.5","L":"100@1.70","H":"100@2.02"}],"ID":"e1c9fa9e-dfbc-406c-b9a7-f612fd21d470","POOLSTATUS":"Payout","INPLAY":"false","ALLUP":"true","Cur":"1"},"fhlodds":{"LINELIST":[{"LINENUM":"1","MAINLINE":"true","LINESTATUS":"1","LINEORDER":"1","LINE":"1.5/1.5","L":"100@1.30","H":"100@3.20"}],"ID":"866ab7d4-1bf0-4954-87ce-8104cee4473d","POOLSTATUS":"Payout","INPLAY":"false","ALLUP":"true","Cur":"1"},"hasExtraTimePools":false,"results":{"OOE":"O","FHA":"A","FTS":"A","CRS":"00:01","HFT":"A:A","TTG":"+1","FCS":"00:01","HAD":"A"},"definedPools":[],"inplayPools":[]}